link_migration/example_migrations/__init__.py
link_migration/example_migrations/conf.py
link_migration/example_migrations/delete_upgrade.py
link_migration/example_migrations/exception.py
link_migration/example_migrations/hello_world.py
link_migration/example_migrations/neo4j_match_query.py
link_migration/example_migrations/neo4j_update_datetimes_format_iso.py
link_migration/example_migrations/using_self.py
link_migration/example_migrations/without_docstring.py
link_migration/framework/__init__.py
link_migration/framework/changelog.py
link_migration/framework/migration.py
link_migration/framework/model.py
link_migration/framework/runner.py
link_migration/framework/version.py
link_migration/framework/views.py
link_migration/framework/generation/__init__.py
link_migration/tests/__init__.py
link_migration/tests/acceptance/__init__.py
link_migration/tests/unit/__init__.py
link_migration/tests/unit/test_formater_message.py
link_migration/tests/unit/test_migration_wrapper.py
link_migration/tests/unit/test_terminal_messages.py
link_migration/tests/unit/test_version.py
link_migration-0.0.21.dist-info/METADATA
link_migration-0.0.21.dist-info/WHEEL
link_migration-0.0.21.dist-info/entry_points.txt
link_migration-0.0.21.dist-info/top_level.txt
link_migration-0.0.21.dist-info/RECORD
