Metadata-Version: 2.1
Name: link-migration
Version: 0.0.21
Summary: A generic tool for migrate in python.
Home-page: https://github.com/takamuffin/link-migration
Author: Alex Sansone
Author-email: aeris1987@gmail.com
License: MIT
Keywords: migration
Platform: UNKNOWN
Classifier: Programming Language :: Python :: 3
Classifier: Programming Language :: Python :: 3.6
Classifier: License :: OSI Approved :: MIT License
Classifier: Operating System :: OS Independent
Requires-Dist: termcolor
